omni_comment/__init__.py
omni_comment/acquire_lock.py
omni_comment/comments.py
omni_comment/logger.py
omni_comment/main.py
omni_comment/metadata.py
omni_comment/retry.py
omni_comment/utils.py
omni_comment/tests/__init__.py
omni_comment/tests/test_main.py
omni_comment-1.0.3.dist-info/METADATA
omni_comment-1.0.3.dist-info/WHEEL
omni_comment-1.0.3.dist-info/licenses/LICENSE
omni_comment-1.0.3.dist-info/RECORD
