Metadata-Version: 2.4
Name: omni-comment
Version: 1.0.3
Summary: Combine outputs from many jobs into a single comment
Project-URL: Homepage, https://github.com/mskelton/omni-commen-py
Project-URL: Issues, https://github.com/mskelton/omni-comment-py/issues
Author: Mark Skelton
License-Expression: ISC
License-File: LICENSE
Keywords: comment,github
Requires-Python: >=3.10
Requires-Dist: httpx>=0.27.0
Requires-Dist: pyyaml>=6.0
